memory_controller.vhd
-- ============================================================
-- memory_controller.vhd
-- FSM Moore: copia ROM->RAM y permite acceso externo
-- Estados: IDLE, READ_ROM, WAIT_ROM, WAIT_ROM2,
--          WRITE_RAM, READ_RAM, DONE
-- ============================================================

library ieee;
use ieee.std_logic_1164.all;
use ieee.numeric_std.all;
use work.mem_pkg.all;

entity memory_controller is
  port (
    clk          : in  std_logic;
    rst          : in  std_logic;
    rom_re       : out std_logic;
    rom_addr     : out addr_word;
    rom_data     : in  data_word;
    ram_we       : out std_logic;
    ram_re       : out std_logic;
    ram_addr     : out addr_word;
    ram_data_in  : out data_word;
    ram_data_out : in  data_word;
    ext_we       : in  std_logic;
    ext_re       : in  std_logic;
    ext_addr     : in  addr_word;
    ext_data_in  : in  data_word;
    data_out     : out data_word;
    done         : out std_logic
  );
end entity memory_controller;

architecture rtl of memory_controller is

  type state_type is (S_IDLE, S_READ_ROM, S_WAIT_ROM, S_WAIT_ROM2, S_WRITE_RAM, S_READ_RAM, S_DONE);

  signal state        : state_type := S_IDLE;
  signal addr_counter : integer range 0 to 2**ADDR_WIDTH-1 := 0;

  signal s_rom_re      : std_logic := '0';
  signal s_ram_we      : std_logic := '0';
  signal s_ram_re      : std_logic := '0';
  signal s_rom_addr    : addr_word := (others => '0');
  signal s_ram_addr    : addr_word := (others => '0');
  signal s_ram_data_in : data_word := (others => '0');
  signal done_reg      : std_logic := '0';
  signal rom_data_reg  : data_word := (others => '0');

begin

  process(clk)
  begin
    if rising_edge(clk) then
      if rst = '1' then
        state         <= S_IDLE;
        addr_counter  <= 0;
        done_reg      <= '0';
        clear_control_signals(s_rom_re, s_ram_we, s_ram_re);
        s_rom_addr    <= (others => '0');
        s_ram_addr    <= (others => '0');
        s_ram_data_in <= (others => '0');
        rom_data_reg  <= (others => '0');

      else
        case state is

          when S_IDLE =>
            clear_control_signals(s_rom_re, s_ram_we, s_ram_re);
            addr_counter <= 0;
            done_reg     <= '0';
            state        <= S_READ_ROM;

          -- Ciclo 1: presenta direccion, activa re
          when S_READ_ROM =>
            clear_control_signals(s_rom_re, s_ram_we, s_ram_re);
            s_rom_re   <= '1';
            s_rom_addr <= std_logic_vector(to_unsigned(addr_counter, ADDR_WIDTH));
            state      <= S_WAIT_ROM;

          -- Ciclo 2: ROM registra direccion en flanco, dato aun no valido
          when S_WAIT_ROM =>
            clear_control_signals(s_rom_re, s_ram_we, s_ram_re);
            s_rom_re   <= '1';
            s_rom_addr <= std_logic_vector(to_unsigned(addr_counter, ADDR_WIDTH));
            state      <= S_WAIT_ROM2;

          -- Ciclo 3: dato ROM valido en la salida, capturamos
          when S_WAIT_ROM2 =>
            clear_control_signals(s_rom_re, s_ram_we, s_ram_re);
            rom_data_reg <= rom_data;  -- ahora si es valido
            state        <= S_WRITE_RAM;

          -- Ciclo 4: escribe en RAM
          when S_WRITE_RAM =>
            clear_control_signals(s_rom_re, s_ram_we, s_ram_re);
            s_ram_we      <= '1';
            s_ram_addr    <= std_logic_vector(to_unsigned(addr_counter, ADDR_WIDTH));
            s_ram_data_in <= rom_data_reg;
            state         <= S_READ_RAM;

          -- Ciclo 5: lee RAM para verificacion, avanza
          when S_READ_RAM =>
            clear_control_signals(s_rom_re, s_ram_we, s_ram_re);
            s_ram_re   <= '1';
            s_ram_addr <= std_logic_vector(to_unsigned(addr_counter, ADDR_WIDTH));
            if addr_counter =  2**ADDR_WIDTH - 1 then
              state <= S_DONE;
            else
              addr_counter <= addr_counter + 1;
              state        <= S_READ_ROM;
            end if;

          when S_DONE =>
            done_reg      <= '1';
            s_ram_we      <= ext_we;
            s_ram_re      <= ext_re;
            s_ram_addr    <= ext_addr;
            s_ram_data_in <= ext_data_in;
            s_rom_re      <= '0';
            s_rom_addr    <= (others => '0');

          when others =>
            state <= S_IDLE;

        end case;
      end if;
    end if;
  end process;

  rom_re      <= s_rom_re;
  rom_addr    <= s_rom_addr;
  ram_we      <= s_ram_we;
  ram_re      <= s_ram_re;
  ram_addr    <= s_ram_addr;
  ram_data_in <= s_ram_data_in;
  done        <= done_reg;
  data_out    <= ram_data_out;

end architecture rtl;

ram_sincrona.vhd
-- =============================================================
-- ram_sincrona.vhd
-- RAM sincrona 16x8, lectura/escritura parametrizable
-- Universidad del Cauca - SENA Ficha 3229446
-- Andre Lopez - Mayo 2026
-- =============================================================
library ieee;
use ieee.std_logic_1164.all;
use ieee.numeric_std.all;
use work.mem_pkg.all;

entity ram_sincrona is
  generic (
    DATA_WIDTH : positive := 8;
    ADDR_WIDTH : positive := 4;
    RDW_MODE   : string   := "READ_FIRST"
  );
  port (
    clk      : in  std_logic;
    rd_en    : in  std_logic;
    wr_en    : in  std_logic;
    addr     : in  addr_t;
    data_in  : in  word_t;
    data_out : out word_t
  );
end entity ram_sincrona;

architecture rtl of ram_sincrona is

  type ram_type is array (0 to 2**ADDR_WIDTH-1) of word_t;
  signal mem   : ram_type;
  signal q_reg : word_t := (others => '0');

  attribute ramstyle        : string;
  attribute ramstyle of mem : signal is "M9K";

begin

  process(clk)
    variable idx : integer range 0 to 2**ADDR_WIDTH-1;
  begin
    if rising_edge(clk) then
      idx := to_integer(unsigned(addr));
      if wr_en = '1' then
        mem(idx) <= data_in;
        if    RDW_MODE = "WRITE_FIRST" then q_reg <= data_in;
        elsif RDW_MODE = "READ_FIRST"  then q_reg <= mem(idx);
        end if;
      elsif rd_en = '1' then
        q_reg <= mem(idx);
      end if;
    end if;
  end process;

  data_out <= q_reg;

end architecture rtl;

rom_sync.vhd
-- =============================================================
-- rom_sync.vhd
-- ROM sincrona 16x8 inicializada con datos predefinidos
-- Universidad del Cauca - SENA Ficha 3229446
-- Andre Lopez - Mayo 2026
-- =============================================================
library ieee;
use ieee.std_logic_1164.all;
use ieee.numeric_std.all;
use work.mem_pkg.all;

entity rom_sync is
  port (
    clk      : in  std_logic;
    re       : in  std_logic;
    addr     : in  addr_t;
    data_out : out word_t
  );
end entity rom_sync;

architecture rtl of rom_sync is

  constant rom_mem : mem_t := (
    0  => x"AA",
    1  => x"55",
    2  => x"F0",
    3  => x"0F",
    4  => x"FF",
    5  => x"00",
    6  => x"A5",
    7  => x"5A",
    8  => x"12",
    9  => x"34",
    10 => x"56",
    11 => x"78",
    12 => x"9A",
    13 => x"BC",
    14 => x"DE",
    15 => x"EF"
  );

  signal q_reg : word_t := (others => '0');

  attribute romstyle : string;
  attribute romstyle of rom_mem : constant is "M9K";

begin

  process(clk)
  begin
    if rising_edge(clk) then
      if re = '1' then
        q_reg <= rom_mem(to_integer(unsigned(addr)));
      end if;
    end if;
  end process;

  data_out <= q_reg;

end architecture rtl;

memory_system_top.vhd
-- =============================================================
-- memory_system_top.vhd
-- Top-level estructural: ROM + RAM + FSM
-- Señales externas: clk, rst, addr, data_in, data_out, we, re
-- =============================================================
library ieee;
use ieee.std_logic_1164.all;
use ieee.numeric_std.all;
use work.mem_pkg.all;

entity memory_system_top is
  port (
    clk      : in  std_logic;
    rst      : in  std_logic;
    -- Señales de acceso externo (activas después de done)
    addr     : in  addr_word;
    data_in  : in  data_word;
    we       : in  std_logic;
    re       : in  std_logic;
    -- Salidas
    data_out : out data_word;
    done     : out std_logic
  );
end entity memory_system_top;

architecture structural of memory_system_top is

  -- -------------------------------------------------------
  -- Señales internas entre controlador y memorias
  -- -------------------------------------------------------
  signal rom_re_s      : std_logic;
  signal rom_addr_s    : addr_word;
  signal rom_data_s    : data_word;

  signal ram_we_s      : std_logic;
  signal ram_re_s      : std_logic;
  signal ram_addr_s    : addr_word;
  signal ram_din_s     : data_word;
  signal ram_dout_s    : data_word;

  signal data_out_s    : data_word;
  signal done_s        : std_logic;

begin

  -- -------------------------------------------------------
  -- Instancia ROM síncrona
  -- -------------------------------------------------------
  u_rom : component rom_sync
    generic map (
      DATA_WIDTH => DATA_WIDTH,
      ADDR_WIDTH => ADDR_WIDTH
    )
    port map (
      clk      => clk,
      re       => rom_re_s,
      addr     => rom_addr_s,
      data_out => rom_data_s
    );

  -- -------------------------------------------------------
  -- Instancia RAM síncrona
  -- -------------------------------------------------------
  u_ram : component ram_sincrona
    generic map (
      DATA_WIDTH => DATA_WIDTH,
      ADDR_WIDTH => ADDR_WIDTH,
      RDW_MODE   => "READ_FIRST"
    )
    port map (
      clk      => clk,
      rd_en    => ram_re_s,
      wr_en    => ram_we_s,
      addr     => ram_addr_s,
      data_in  => ram_din_s,
      data_out => ram_dout_s
    );

  -- -------------------------------------------------------
  -- Instancia controlador FSM
  -- -------------------------------------------------------
  u_ctrl : component memory_controller
    port map (
      clk          => clk,
      rst          => rst,
      rom_re       => rom_re_s,
      rom_addr     => rom_addr_s,
      rom_data     => rom_data_s,
      ram_we       => ram_we_s,
      ram_re       => ram_re_s,
      ram_addr     => ram_addr_s,
      ram_data_in  => ram_din_s,
      ram_data_out => ram_dout_s,
      ext_we       => we,
      ext_re       => re,
      ext_addr     => addr,
      ext_data_in  => data_in,
      data_out     => data_out_s,
      done         => done_s
    );

  -- -------------------------------------------------------
  -- Salidas del top-level
  -- -------------------------------------------------------
  data_out <= data_out_s;
  done     <= done_s;

end architecture structural;

tb_memory_system.vhd
-- =============================================================
-- tb_memory_system.vhd 
-- =============================================================
library ieee;
use ieee.std_logic_1164.all;
use ieee.numeric_std.all;
use work.mem_pkg.all;

entity tb_memory_system is
end entity tb_memory_system;

architecture sim of tb_memory_system is

  constant CLK_PERIOD : time := 20 ns;

  signal clk_tb      : std_logic := '0';
  signal rst_tb      : std_logic := '1';
  signal addr_tb     : addr_word := (others => '0');
  signal data_in_tb  : data_word := (others => '0');
  signal we_tb       : std_logic := '0';
  signal re_tb       : std_logic := '0';
  signal data_out_tb : data_word;
  signal done_tb     : std_logic;

  constant rom_expected : mem_t := (
    0  => x"AA", 1  => x"55", 2  => x"F0", 3  => x"0F",
    4  => x"FF", 5  => x"00", 6  => x"A5", 7  => x"5A",
    8  => x"12", 9  => x"34", 10 => x"56", 11 => x"78",
    12 => x"9A", 13 => x"BC", 14 => x"DE", 15 => x"EF"
  );

  procedure wait_cycles(n : integer; signal clk : in std_logic) is
  begin
    for i in 1 to n loop
      wait until rising_edge(clk);
    end loop;
  end procedure;

begin

  DUT : entity work.memory_system_top
    port map (
      clk      => clk_tb,
      rst      => rst_tb,
      addr     => addr_tb,
      data_in  => data_in_tb,
      we       => we_tb,
      re       => re_tb,
      data_out => data_out_tb,
      done     => done_tb
    );

  clk_process : process
  begin
    clk_tb <= '0'; wait for CLK_PERIOD / 2;
    clk_tb <= '1'; wait for CLK_PERIOD / 2;
  end process;

  stimulus : process

    -- Lee una posicion de RAM y devuelve el dato observado
    -- Espera 3 ciclos para cubrir latencia de RAM + controlador
    procedure leer_ram(addr_val : in integer) is
    begin
      addr_tb <= std_logic_vector(to_unsigned(addr_val, ADDR_WIDTH));
      re_tb   <= '1';
      wait_cycles(1, clk_tb);  -- ciclo para que addr llegue a RAM
      wait_cycles(1, clk_tb);  -- ciclo de latencia RAM (dato capturado)
      wait_cycles(1, clk_tb);  -- ciclo extra de estabilizacion
      re_tb <= '0';
    end procedure;

  begin

    -- D. Reset inicial
    report "=== D. Reset inicial ===" severity note;
    rst_tb <= '1';
    wait_cycles(3, clk_tb);
    rst_tb <= '0';
    report "=== Reset liberado ===" severity note;

    -- A. Esperar copia automatica ROM -> RAM
    report "=== A. Esperando copia ROM->RAM ===" severity note;
    wait until done_tb = '1';
    wait_cycles(3, clk_tb);  -- estabilizacion post-done
    report "=== Copia completa. done=1 ===" severity note;

    -- C. Verificar datos copiados en RAM
    report "=== C. Verificando datos en RAM ===" severity note;

    for i in 0 to MEM_DEPTH-1 loop
      leer_ram(i);
      assert data_out_tb = rom_expected(i)
        report "FALLO RAM pos " & integer'image(i)
        severity error;
    end loop;

    report "=== Lectura RAM OK ===" severity note;

    -- B. Escritura externa manual en RAM[0]
    report "=== B. Escritura externa RAM[0] <- 0xC3 ===" severity note;
    addr_tb    <= x"0";
    data_in_tb <= x"C3";
    we_tb      <= '1';
    wait_cycles(2, clk_tb);  -- 2 ciclos para asegurar escritura
    we_tb <= '0';
    wait_cycles(1, clk_tb);

    -- Leer de vuelta RAM[0]
    leer_ram(0);
    assert data_out_tb = x"C3"
      report "FALLO escritura manual RAM[0]"
      severity error;
    report "=== Escritura/lectura manual OK ===" severity note;

    -- D. Reset en caliente
    report "=== D. Reset en caliente ===" severity note;
    rst_tb <= '1';
    wait_cycles(2, clk_tb);
    rst_tb <= '0';
    wait_cycles(1, clk_tb);
    assert done_tb = '0'
      report "FALLO: done debe ser 0 tras reset"
      severity error;

    -- Esperar segunda copia completa
    wait until done_tb = '1';
    report "=== Segunda copia completa tras reset ===" severity note;

    report "=== SIMULACION FINALIZADA ===" severity note;
    wait;

  end process stimulus;

end architecture sim;

ondas.vcd
$date
  Sat May  2 01:42:21 2026
$end
$version
  GHDL v0
$end
$timescale
  1 fs
$end
$scope module standard $end
$upscope $end
$scope module textio $end
$upscope $end
$scope module std_logic_1164 $end
$upscope $end
$scope module numeric_std $end
$upscope $end
$scope module mem_pkg $end
$upscope $end
$scope module tb_memory_system $end
$var reg 1 ! clk_tb $end
$var reg 1 " rst_tb $end
$var reg 4 # addr_tb[3:0] $end
$var reg 8 $ data_in_tb[7:0] $end
$var reg 1 % we_tb $end
$var reg 1 & re_tb $end
$var reg 8 ' data_out_tb[7:0] $end
$var reg 1 ( done_tb $end
$scope module dut $end
$var reg 1 ) clk $end
$var reg 1 * rst $end
$var reg 4 + addr[3:0] $end
$var reg 8 , data_in[7:0] $end
$var reg 1 - we $end
$var reg 1 . re $end
$var reg 8 / data_out[7:0] $end
$var reg 1 0 done $end
$var reg 1 1 rom_re_s $end
$var reg 4 2 rom_addr_s[3:0] $end
$var reg 8 3 rom_data_s[7:0] $end
$var reg 1 4 ram_we_s $end
$var reg 1 5 ram_re_s $end
$var reg 4 6 ram_addr_s[3:0] $end
$var reg 8 7 ram_din_s[7:0] $end
$var reg 8 8 ram_dout_s[7:0] $end
$var reg 8 9 data_out_s[7:0] $end
$var reg 1 : done_s $end
$scope module u_rom $end
$var reg 1 ; clk $end
$var reg 1 < re $end
$var reg 4 = addr[3:0] $end
$var reg 8 > data_out[7:0] $end
$var reg 8 ? q_reg[7:0] $end
$upscope $end
$scope module u_ram $end
$var reg 1 @ clk $end
$var reg 1 A rd_en $end
$var reg 1 B wr_en $end
$var reg 4 C addr[3:0] $end
$var reg 8 D data_in[7:0] $end
$var reg 8 E data_out[7:0] $end
$comment mem is not handled $end
$var reg 8 F q_reg[7:0] $end
$upscope $end
$scope module u_ctrl $end
$var reg 1 G clk $end
$var reg 1 H rst $end
$var reg 1 I rom_re $end
$var reg 4 J rom_addr[3:0] $end
$var reg 8 K rom_data[7:0] $end
$var reg 1 L ram_we $end
$var reg 1 M ram_re $end
$var reg 4 N ram_addr[3:0] $end
$var reg 8 O ram_data_in[7:0] $end
$var reg 8 P ram_data_out[7:0] $end
$var reg 1 Q ext_we $end
$var reg 1 R ext_re $end
$var reg 4 S ext_addr[3:0] $end
$var reg 8 T ext_data_in[7:0] $end
$var reg 8 U data_out[7:0] $end
$var reg 1 V done $end
$comment state is not handled $end
$var integer 32 W addr_counter $end
$var reg 1 X s_rom_re $end
$var reg 1 Y s_ram_we $end
$var reg 1 Z s_ram_re $end
$var reg 4 [ s_rom_addr[3:0] $end
$var reg 4 \ s_ram_addr[3:0] $end
$var reg 8 ] s_ram_data_in[7:0] $end
$var reg 1 ^ done_reg $end
$var reg 8 _ rom_data_reg[7:0] $end
$upscope $end
$upscope $end
$upscope $end
$enddefinitions $end
#0
0!
1"
b0000 #
b00000000 $
0%
0&
b00000000 '
0(
0)
1*
b0000 +
b00000000 ,
0-
0.
b00000000 /
00
01
b0000 2
b00000000 3
04
05
b0000 6
b00000000 7
b00000000 8
b00000000 9
0:
0;
0<
b0000 =
b00000000 >
b00000000 ?
0@
0A
0B
b0000 C
b00000000 D
b00000000 E
b00000000 F
0G
1H
0I
b0000 J
b00000000 K
0L
0M
b0000 N
b00000000 O
b00000000 P
0Q
0R
b0000 S
b00000000 T
b00000000 U
0V
b0 W
0X
0Y
0Z
b0000 [
b0000 \
b00000000 ]
0^
b00000000 _
#10000000
1!
1)
1;
1@
1G
#20000000
0!
0)
0;
0@
0G
#30000000
1!
1)
1;
1@
1G
#40000000
0!
0)
0;
0@
0G
#50000000
1!
0"
1)
0*
1;
1@
1G
0H
#60000000
0!
0)
0;
0@
0G
#70000000
1!
1)
1;
1@
1G
#80000000
0!
0)
0;
0@
0G
#90000000
1!
1)
11
1;
1<
1@
1G
1I
1X
#100000000
0!
0)
0;
0@
0G
#110000000
1!
1)
b10101010 3
1;
b10101010 >
b10101010 ?
1@
1G
b10101010 K
#120000000
0!
0)
0;
0@
0G
#130000000
1!
1)
01
1;
0<
1@
1G
0I
0X
b10101010 _
#140000000
0!
0)
0;
0@
0G
#150000000
1!
1)
14
b10101010 7
1;
1@
1B
b10101010 D
1G
1L
b10101010 O
1Y
b10101010 ]
#160000000
0!
0)
0;
0@
0G
#170000000
1!
bUUUUUUUU '
1)
bUUUUUUUU /
04
15
bUUUUUUUU 8
bUUUUUUUU 9
1;
1@
1A
0B
bUUUUUUUU E
bUUUUUUUU F
1G
0L
1M
bUUUUUUUU P
bUUUUUUUU U
b1 W
0Y
1Z
#180000000
0!
0)
0;
0@
0G
#190000000
1!
b10101010 '
1)
b10101010 /
11
b0001 2
05
b10101010 8
b10101010 9
1;
1<
b0001 =
1@
0A
b10101010 E
b10101010 F
1G
1I
b0001 J
0M
b10101010 P
b10101010 U
1X
0Z
b0001 [
#200000000
0!
0)
0;
0@
0G
#210000000
1!
1)
b01010101 3
1;
b01010101 >
b01010101 ?
1@
1G
b01010101 K
#220000000
0!
0)
0;
0@
0G
#230000000
1!
1)
01
1;
0<
1@
1G
0I
0X
b01010101 _
#240000000
0!
0)
0;
0@
0G
#250000000
1!
1)
14
b0001 6
b01010101 7
1;
1@
1B
b0001 C
b01010101 D
1G
1L
b0001 N
b01010101 O
1Y
b0001 \
b01010101 ]
#260000000
0!
0)
0;
0@
0G
#270000000
1!
bUUUUUUUU '
1)
bUUUUUUUU /
04
15
bUUUUUUUU 8
bUUUUUUUU 9
1;
1@
1A
0B
bUUUUUUUU E
bUUUUUUUU F
1G
0L
1M
bUUUUUUUU P
bUUUUUUUU U
b10 W
0Y
1Z
#280000000
0!
0)
0;
0@
0G
#290000000
1!
b01010101 '
1)
b01010101 /
11
b0010 2
05
b01010101 8
b01010101 9
1;
1<
b0010 =
1@
0A
b01010101 E
b01010101 F
1G
1I
b0010 J
0M
b01010101 P
b01010101 U
1X
0Z
b0010 [
#300000000
0!
0)
0;
0@
0G
#310000000
1!
1)
b11110000 3
1;
b11110000 >
b11110000 ?
1@
1G
b11110000 K
#320000000
0!
0)
0;
0@
0G
#330000000
1!
1)
01
1;
0<
1@
1G
0I
0X
b11110000 _
#340000000
0!
0)
0;
0@
0G
#350000000
1!
1)
14
b0010 6
b11110000 7
1;
1@
1B
b0010 C
b11110000 D
1G
1L
b0010 N
b11110000 O
1Y
b0010 \
b11110000 ]
#360000000
0!
0)
0;
0@
0G
#370000000
1!
bUUUUUUUU '
1)
bUUUUUUUU /
04
15
bUUUUUUUU 8
bUUUUUUUU 9
1;
1@
1A
0B
bUUUUUUUU E
bUUUUUUUU F
1G
0L
1M
bUUUUUUUU P
bUUUUUUUU U
b11 W
0Y
1Z
#380000000
0!
0)
0;
0@
0G
#390000000
1!
b11110000 '
1)
b11110000 /
11
b0011 2
05
b11110000 8
b11110000 9
1;
1<
b0011 =
1@
0A
b11110000 E
b11110000 F
1G
1I
b0011 J
0M
b11110000 P
b11110000 U
1X
0Z
b0011 [
#400000000
0!
0)
0;
0@
0G
#410000000
1!
1)
b00001111 3
1;
b00001111 >
b00001111 ?
1@
1G
b00001111 K
#420000000
0!
0)
0;
0@
0G
#430000000
1!
1)
01
1;
0<
1@
1G
0I
0X
b00001111 _
#440000000
0!
0)
0;
0@
0G
#450000000
1!
1)
14
b0011 6
b00001111 7
1;
1@
1B
b0011 C
b00001111 D
1G
1L
b0011 N
b00001111 O
1Y
b0011 \
b00001111 ]
#460000000
0!
0)
0;
0@
0G
#470000000
1!
bUUUUUUUU '
1)
bUUUUUUUU /
04
15
bUUUUUUUU 8
bUUUUUUUU 9
1;
1@
1A
0B
bUUUUUUUU E
bUUUUUUUU F
1G
0L
1M
bUUUUUUUU P
bUUUUUUUU U
b100 W
0Y
1Z
#480000000
0!
0)
0;
0@
0G
#490000000
1!
b00001111 '
1)
b00001111 /
11
b0100 2
05
b00001111 8
b00001111 9
1;
1<
b0100 =
1@
0A
b00001111 E
b00001111 F
1G
1I
b0100 J
0M
b00001111 P
b00001111 U
1X
0Z
b0100 [
#500000000
0!
0)
0;
0@
0G
#510000000
1!
1)
b11111111 3
1;
b11111111 >
b11111111 ?
1@
1G
b11111111 K
#520000000
0!
0)
0;
0@
0G
#530000000
1!
1)
01
1;
0<
1@
1G
0I
0X
b11111111 _
#540000000
0!
0)
0;
0@
0G
#550000000
1!
1)
14
b0100 6
b11111111 7
1;
1@
1B
b0100 C
b11111111 D
1G
1L
b0100 N
b11111111 O
1Y
b0100 \
b11111111 ]
#560000000
0!
0)
0;
0@
0G
#570000000
1!
bUUUUUUUU '
1)
bUUUUUUUU /
04
15
bUUUUUUUU 8
bUUUUUUUU 9
1;
1@
1A
0B
bUUUUUUUU E
bUUUUUUUU F
1G
0L
1M
bUUUUUUUU P
bUUUUUUUU U
b101 W
0Y
1Z
#580000000
0!
0)
0;
0@
0G
#590000000
1!
b11111111 '
1)
b11111111 /
11
b0101 2
05
b11111111 8
b11111111 9
1;
1<
b0101 =
1@
0A
b11111111 E
b11111111 F
1G
1I
b0101 J
0M
b11111111 P
b11111111 U
1X
0Z
b0101 [
#600000000
0!
0)
0;
0@
0G
#610000000
1!
1)
b00000000 3
1;
b00000000 >
b00000000 ?
1@
1G
b00000000 K
#620000000
0!
0)
0;
0@
0G
#630000000
1!
1)
01
1;
0<
1@
1G
0I
0X
b00000000 _
#640000000
0!
0)
0;
0@
0G
#650000000
1!
1)
14
b0101 6
b00000000 7
1;
1@
1B
b0101 C
b00000000 D
1G
1L
b0101 N
b00000000 O
1Y
b0101 \
b00000000 ]
#660000000
0!
0)
0;
0@
0G
#670000000
1!
bUUUUUUUU '
1)
bUUUUUUUU /
04
15
bUUUUUUUU 8
bUUUUUUUU 9
1;
1@
1A
0B
bUUUUUUUU E
bUUUUUUUU F
1G
0L
1M
bUUUUUUUU P
bUUUUUUUU U
b110 W
0Y
1Z
#680000000
0!
0)
0;
0@
0G
#690000000
1!
b00000000 '
1)
b00000000 /
11
b0110 2
05
b00000000 8
b00000000 9
1;
1<
b0110 =
1@
0A
b00000000 E
b00000000 F
1G
1I
b0110 J
0M
b00000000 P
b00000000 U
1X
0Z
b0110 [
#700000000
0!
0)
0;
0@
0G
#710000000
1!
1)
b10100101 3
1;
b10100101 >
b10100101 ?
1@
1G
b10100101 K
#720000000
0!
0)
0;
0@
0G
#730000000
1!
1)
01
1;
0<
1@
1G
0I
0X
b10100101 _
#740000000
0!
0)
0;
0@
0G
#750000000
1!
1)
14
b0110 6
b10100101 7
1;
1@
1B
b0110 C
b10100101 D
1G
1L
b0110 N
b10100101 O
1Y
b0110 \
b10100101 ]
#760000000
0!
0)
0;
0@
0G
#770000000
1!
bUUUUUUUU '
1)
bUUUUUUUU /
04
15
bUUUUUUUU 8
bUUUUUUUU 9
1;
1@
1A
0B
bUUUUUUUU E
bUUUUUUUU F
1G
0L
1M
bUUUUUUUU P
bUUUUUUUU U
b111 W
0Y
1Z
#780000000
0!
0)
0;
0@
0G
#790000000
1!
b10100101 '
1)
b10100101 /
11
b0111 2
05
b10100101 8
b10100101 9
1;
1<
b0111 =
1@
0A
b10100101 E
b10100101 F
1G
1I
b0111 J
0M
b10100101 P
b10100101 U
1X
0Z
b0111 [
#800000000
0!
0)
0;
0@
0G
#810000000
1!
1)
b01011010 3
1;
b01011010 >
b01011010 ?
1@
1G
b01011010 K
#820000000
0!
0)
0;
0@
0G
#830000000
1!
1)
01
1;
0<
1@
1G
0I
0X
b01011010 _
#840000000
0!
0)
0;
0@
0G
#850000000
1!
1)
14
b0111 6
b01011010 7
1;
1@
1B
b0111 C
b01011010 D
1G
1L
b0111 N
b01011010 O
1Y
b0111 \
b01011010 ]
#860000000
0!
0)
0;
0@
0G
#870000000
1!
bUUUUUUUU '
1)
bUUUUUUUU /
04
15
bUUUUUUUU 8
bUUUUUUUU 9
1;
1@
1A
0B
bUUUUUUUU E
bUUUUUUUU F
1G
0L
1M
bUUUUUUUU P
bUUUUUUUU U
b1000 W
0Y
1Z
#880000000
0!
0)
0;
0@
0G
#890000000
1!
b01011010 '
1)
b01011010 /
11
b1000 2
05
b01011010 8
b01011010 9
1;
1<
b1000 =
1@
0A
b01011010 E
b01011010 F
1G
1I
b1000 J
0M
b01011010 P
b01011010 U
1X
0Z
b1000 [
#900000000
0!
0)
0;
0@
0G
#910000000
1!
1)
b00010010 3
1;
b00010010 >
b00010010 ?
1@
1G
b00010010 K
#920000000
0!
0)
0;
0@
0G
#930000000
1!
1)
01
1;
0<
1@
1G
0I
0X
b00010010 _
#940000000
0!
0)
0;
0@
0G
#950000000
1!
1)
14
b1000 6
b00010010 7
1;
1@
1B
b1000 C
b00010010 D
1G
1L
b1000 N
b00010010 O
1Y
b1000 \
b00010010 ]
#960000000
0!
0)
0;
0@
0G
#970000000
1!
bUUUUUUUU '
1)
bUUUUUUUU /
04
15
bUUUUUUUU 8
bUUUUUUUU 9
1;
1@
1A
0B
bUUUUUUUU E
bUUUUUUUU F
1G
0L
1M
bUUUUUUUU P
bUUUUUUUU U
b1001 W
0Y
1Z
#980000000
0!
0)
0;
0@
0G
#990000000
1!
b00010010 '
1)
b00010010 /
11
b1001 2
05
b00010010 8
b00010010 9
1;
1<
b1001 =
1@
0A
b00010010 E
b00010010 F
1G
1I
b1001 J
0M
b00010010 P
b00010010 U
1X
0Z
b1001 [
#1000000000
0!
0)
0;
0@
0G
#1010000000
1!
1)
b00110100 3
1;
b00110100 >
b00110100 ?
1@
1G
b00110100 K
#1020000000
0!
0)
0;
0@
0G
#1030000000
1!
1)
01
1;
0<
1@
1G
0I
0X
b00110100 _
#1040000000
0!
0)
0;
0@
0G
#1050000000
1!
1)
14
b1001 6
b00110100 7
1;
1@
1B
b1001 C
b00110100 D
1G
1L
b1001 N
b00110100 O
1Y
b1001 \
b00110100 ]
#1060000000
0!
0)
0;
0@
0G
#1070000000
1!
bUUUUUUUU '
1)
bUUUUUUUU /
04
15
bUUUUUUUU 8
bUUUUUUUU 9
1;
1@
1A
0B
bUUUUUUUU E
bUUUUUUUU F
1G
0L
1M
bUUUUUUUU P
bUUUUUUUU U
b1010 W
0Y
1Z
#1080000000
0!
0)
0;
0@
0G
#1090000000
1!
b00110100 '
1)
b00110100 /
11
b1010 2
05
b00110100 8
b00110100 9
1;
1<
b1010 =
1@
0A
b00110100 E
b00110100 F
1G
1I
b1010 J
0M
b00110100 P
b00110100 U
1X
0Z
b1010 [
#1100000000
0!
0)
0;
0@
0G
#1110000000
1!
1)
b01010110 3
1;
b01010110 >
b01010110 ?
1@
1G
b01010110 K
#1120000000
0!
0)
0;
0@
0G
#1130000000
1!
1)
01
1;
0<
1@
1G
0I
0X
b01010110 _
#1140000000
0!
0)
0;
0@
0G
#1150000000
1!
1)
14
b1010 6
b01010110 7
1;
1@
1B
b1010 C
b01010110 D
1G
1L
b1010 N
b01010110 O
1Y
b1010 \
b01010110 ]
#1160000000
0!
0)
0;
0@
0G
#1170000000
1!
bUUUUUUUU '
1)
bUUUUUUUU /
04
15
bUUUUUUUU 8
bUUUUUUUU 9
1;
1@
1A
0B
bUUUUUUUU E
bUUUUUUUU F
1G
0L
1M
bUUUUUUUU P
bUUUUUUUU U
b1011 W
0Y
1Z
#1180000000
0!
0)
0;
0@
0G
#1190000000
1!
b01010110 '
1)
b01010110 /
11
b1011 2
05
b01010110 8
b01010110 9
1;
1<
b1011 =
1@
0A
b01010110 E
b01010110 F
1G
1I
b1011 J
0M
b01010110 P
b01010110 U
1X
0Z
b1011 [
#1200000000
0!
0)
0;
0@
0G
#1210000000
1!
1)
b01111000 3
1;
b01111000 >
b01111000 ?
1@
1G
b01111000 K
#1220000000
0!
0)
0;
0@
0G
#1230000000
1!
1)
01
1;
0<
1@
1G
0I
0X
b01111000 _
#1240000000
0!
0)
0;
0@
0G
#1250000000
1!
1)
14
b1011 6
b01111000 7
1;
1@
1B
b1011 C
b01111000 D
1G
1L
b1011 N
b01111000 O
1Y
b1011 \
b01111000 ]
#1260000000
0!
0)
0;
0@
0G
#1270000000
1!
bUUUUUUUU '
1)
bUUUUUUUU /
04
15
bUUUUUUUU 8
bUUUUUUUU 9
1;
1@
1A
0B
bUUUUUUUU E
bUUUUUUUU F
1G
0L
1M
bUUUUUUUU P
bUUUUUUUU U
b1100 W
0Y
1Z
#1280000000
0!
0)
0;
0@
0G
#1290000000
1!
b01111000 '
1)
b01111000 /
11
b1100 2
05
b01111000 8
b01111000 9
1;
1<
b1100 =
1@
0A
b01111000 E
b01111000 F
1G
1I
b1100 J
0M
b01111000 P
b01111000 U
1X
0Z
b1100 [
#1300000000
0!
0)
0;
0@
0G
#1310000000
1!
1)
b10011010 3
1;
b10011010 >
b10011010 ?
1@
1G
b10011010 K
#1320000000
0!
0)
0;
0@
0G
#1330000000
1!
1)
01
1;
0<
1@
1G
0I
0X
b10011010 _
#1340000000
0!
0)
0;
0@
0G
